{
	"name": "Vimium C",
	"@time": "2026. 5. 2. PM 1:18:44",
	"time": 1777695524734,
	"environment": {
		"extension": "2.12.3",
		"platform": "win",
		"firefox": 150
	},
	"exclusionRules": [],
	"grabBackFocus": true,
	"keyLayout": 2,
	"keyMappings": [
		"#!no-check",
		"unmapAll",
		"unmap -",
		"",
		"map f LinkHints.activate",
		"map F LinkHints.activateOpenInNewTab",
		"map j scrollDown",
		"map k scrollUp",
		"map h scrollLeft",
		"map l scrollRight",
		"map gg scrollToTop",
		"map G scrollToBottom",
		"map d scrollPageDown",
		"map u scrollPageUp",
		"map r reloadTab",
		"map + zoomIn",
		"map - zoomOut",
		"map = zoomReset",
		"map yy copyCurrentUrl",
		"map gi focusInput",
		"map yf LinkHints.activateCopyLinkUrl",
		"map yt LinkHints.activateCopyLinkText",
		"map p openCopiedUrlInCurrentTab",
		"map P openCopiedUrlInNewTab",
		"map yi LinkHints.activateCopyImage",
		"map yI LinkHints.activateDownloadImage",
		"map yv LinkHints.activateSelect",
		"map i enterInsertMode",
		"map v enterVisualMode",
		"map V enterVisualLineMode",
		"",
		"",
		"map o Vomnibar.activate",
		"map O Vomnibar.activateInNewTab",
		"map b Vomnibar.activateBookmarks",
		"map B Vomnibar.activateBookmarksInNewTab",
		"map t Vomnibar.activateTabs",
		"map H Vomnibar.activateHistoryInNewTab",
		"map ge Vomnibar.activateEditUrl",
		"map gE Vomnibar.activateEditUrlInNewTab",
		"",
		"",
		"map / enterFindMode",
		"map n performFind",
		"map N performBackwardsFind",
		"",
		"map [b goBack",
		"map ]b goForward",
		"",
		"map gn nextTab",
		"map gp previousTab",
		"map gs firstTab",
		"map gl lastTab",
		"map m togglePinTab",
		"map q visitPreviousTab",
		"map << moveTabLeft",
		"map >> moveTabRight",
		"map x removeTab keepWindow=\"mayClose\" goto=\"previous\"",
		"map X restoreTab",
		"map ? showHelp",
		"",
		"",
		"map z discardTab",
		""
	],
	"newTabUrl": "https://duckduckgo.com",
	"searchEngines": "js\\:|Js: javascript:\\ $S; JavaScript",
	"searchUrl": "https://duckduckgo.com/?q=$s DuckDuckGo",
	"vimSync": true
}
